llm_regression_tester/__init__.py
llm_regression_tester/_version.py
llm_regression_tester/llm_regression_tester.py
llm_regression_tester-0.1.2.dist-info/licenses/LICENSE
llm_regression_tester-0.1.2.dist-info/METADATA
llm_regression_tester-0.1.2.dist-info/WHEEL
llm_regression_tester-0.1.2.dist-info/top_level.txt
llm_regression_tester-0.1.2.dist-info/RECORD
