Metadata-Version: 2.4
Name: llm-regression-tester
Version: 0.1.2
Summary: A flexible library for testing LLM responses against predefined rubrics using OpenAI's API for automated scoring
Home-page: https://github.com/ktech99/llm-regression-tester
Author: LLM Regression Tester Contributors
Author-email: Kartik Arora <kartikarora99@gmail.com>
Maintainer-email: Kartik Arora <kartikarora99@gmail.com>
License: MIT
Project-URL: Homepage, https://github.com/ktech99/llm-regression-tester
Project-URL: Documentation, https://llm-regression-tester.readthedocs.io/
Project-URL: Repository, https://github.com/ktech99/llm-regression-tester.git
Project-URL: Issues, https://github.com/ktech99/llm-regression-tester/issues
Project-URL: Changelog, https://github.com/ktech99/llm-regression-tester/blob/main/CHANGELOG.md
Keywords: llm,testing,evaluation,rubrics,ai,nlp
Classifier: Development Status :: 4 - Beta
Classifier: Intended Audience :: Developers
Classifier: Intended Audience :: Science/Research
Classifier: License :: OSI Approved :: MIT License
Classifier: Operating System :: OS Independent
Classifier: Programming Language :: Python :: 3
Classifier: Programming Language :: Python :: 3.8
Classifier: Programming Language :: Python :: 3.9
Classifier: Programming Language :: Python :: 3.10
Classifier: Programming Language :: Python :: 3.11
Classifier: Programming Language :: Python :: 3.12
Classifier: Programming Language :: Python :: Implementation :: CPython
Classifier: Topic :: Scientific/Engineering :: Artificial Intelligence
Classifier: Topic :: Software Development :: Libraries :: Python Modules
Classifier: Topic :: Software Development :: Testing
Classifier: Topic :: Software Development :: Quality Assurance
Classifier: Typing :: Typed
Requires-Python: >=3.8
License-File: LICENSE
Requires-Dist: typing-extensions>=4.0.0
Requires-Dist: openai>=1.0.0
Requires-Dist: python-dotenv>=0.19.0
Dynamic: author
Dynamic: home-page
Dynamic: license-file
Dynamic: requires-python
